aap_core/__init__.py
aap_core/agent.py
aap_core/chain.py
aap_core/guardrail.py
aap_core/orchestration.py
aap_core/prompt_augmenter.py
aap_core/py.typed
aap_core/retriever.py
aap_core/thought.py
aap_core/types.py
aap_core/utils.py
aap_core-0.1.3.dev1.dist-info/WHEEL
aap_core-0.1.3.dev1.dist-info/METADATA
aap_core-0.1.3.dev1.dist-info/RECORD
