Metadata-Version: 2.3
Name: aap-core
Version: 0.1.3.dev1
Summary: Agent design pattern core framework
Keywords: agent,ai,pattern,llm
Author: Ly Hon Quang
Author-email: Ly Hon Quang <lyhonquang@gmail.com>
License: MIT
Classifier: Programming Language :: Python :: 3.10
Classifier: Programming Language :: Python :: 3.11
Classifier: Programming Language :: Python :: 3.12
Classifier: Programming Language :: Python :: 3.13
Classifier: Programming Language :: Python :: 3.14
Classifier: Programming Language :: Python :: 3.15
Classifier: Framework :: Pydantic :: 2
Classifier: Operating System :: OS Independent
Requires-Dist: a2a-sdk>=0.3.12
Requires-Dist: pandas>=2.0.0
Requires-Dist: rouge-score>=0.1.2
Requires-Dist: sacrebleu>=2.5.1
Requires-Python: >=3.10.12
Project-URL: Repository, https://github.com/quanghona/agent_design_pattern.git
